autonvtx/__init__.py
autonvtx-0.1.dist-info/LICENSE
autonvtx-0.1.dist-info/METADATA
autonvtx-0.1.dist-info/WHEEL
autonvtx-0.1.dist-info/top_level.txt
autonvtx-0.1.dist-info/RECORD
