Metadata-Version: 2.1
Name: autonvtx
Version: 0.1
Summary: https://github.com/zasdfgbnm/autonvtx
Home-page: https://github.com/zasdfgbnm/autonvtx
Author: Xiang Gao
Author-email: qasdfgtyuiop@gmail.com
License: MIT
Platform: UNKNOWN
Requires-Dist: torch
